
    [
       {
        "name":"mamatha",
        "date":"14/02/2024",
        "activity_id":"11",
        "id":"11",
        "hours":5
       },
       {
         "name":"mamatha",
         "date":"15/02/2024",
         "activity_id":"12",
         "id":"13",

         "hours":5
        },
       {
        "name":"suresh",
        "date":"15/02/2024",
        "activity_id":"22",
        "id":"23",

        "hours":3

       },
       {
        "name":"yasasri",
        "date":"16/02/2024",
        "activity_id":"33",    
            "id":"33",

        "hours":2

       }
    ]
        

    
